dockss.py
toke.py
toke-0.1.1.dist-info/LICENSE
toke-0.1.1.dist-info/METADATA
toke-0.1.1.dist-info/WHEEL
toke-0.1.1.dist-info/entry_points.txt
toke-0.1.1.dist-info/top_level.txt
toke-0.1.1.dist-info/RECORD
