Metadata-Version: 2.1
Name: toke
Version: 0.1.1
Summary: Tool Of KEaising
Home-page: https://github.com/keaising/toke
Author: keaising
Author-email: keaising@gmail.com
License: UNKNOWN
Platform: UNKNOWN
Requires-Dist: Click
Requires-Dist: python-dotenv
Requires-Dist: tweepy
